open_asr_server/__init__.py
open_asr_server/app.py
open_asr_server/backends/__init__.py
open_asr_server/backends/base.py
open_asr_server/backends/faster_whisper.py
open_asr_server/backends/kyutai_mlx.py
open_asr_server/backends/lightning_whisper.py
open_asr_server/backends/nemo_asr.py
open_asr_server/backends/parakeet.py
open_asr_server/backends/whisper.py
open_asr_server/backends/whisper_cpp.py
open_asr_server/cli.py
open_asr_server/config.py
open_asr_server/formatters.py
open_asr_server/models.py
open_asr_server/routes.py
open_asr_server/utils/__init__.py
open_asr_server/utils/model_cache.py
open_asr_server/utils/rate_limit.py
open_asr_server-0.2.0.dist-info/WHEEL
open_asr_server-0.2.0.dist-info/entry_points.txt
open_asr_server-0.2.0.dist-info/METADATA
open_asr_server-0.2.0.dist-info/RECORD
