Metadata-Version: 2.3
Name: open-asr-server
Version: 0.2.0
Summary: OpenAI-compatible ASR server with pluggable local backends.
Keywords: asr,speech-to-text,openai,fastapi,whisper
Author: codyw912
Author-email: codyw912 <32690983+codyw912@users.noreply.github.com>
License: MIT License
Classifier: License :: OSI Approved :: MIT License
Classifier: Programming Language :: Python :: 3
Classifier: Programming Language :: Python :: 3.11
Classifier: Programming Language :: Python :: 3.12
Classifier: Programming Language :: Python :: 3.13
Classifier: Programming Language :: Python :: 3.14
Classifier: Programming Language :: Python :: Implementation :: CPython
Requires-Dist: fastapi>=0.110
Requires-Dist: huggingface-hub>=0.23
Requires-Dist: pydantic>=2.0
Requires-Dist: python-multipart>=0.0.9
Requires-Dist: typer>=0.12
Requires-Dist: uvicorn>=0.29
Requires-Dist: pytest>=7.4 ; extra == 'dev'
Requires-Dist: pytest-cov>=4.1 ; extra == 'dev'
Requires-Dist: httpx>=0.25 ; extra == 'dev'
Requires-Dist: faster-whisper ; extra == 'faster-whisper'
Requires-Dist: moshi-mlx ; python_full_version == '3.12.*' and extra == 'kyutai-mlx'
Requires-Dist: lightning-whisper-mlx ; python_full_version < '3.12' and extra == 'lightning-whisper'
Requires-Dist: nemo-toolkit[asr] ; extra == 'nemo'
Requires-Dist: torch ; extra == 'nemo'
Requires-Dist: torchaudio ; extra == 'nemo'
Requires-Dist: torchvision ; extra == 'nemo'
Requires-Dist: parakeet-mlx ; python_full_version < '3.12' and extra == 'parakeet'
Requires-Dist: mlx-whisper ; python_full_version < '3.12' and extra == 'whisper'
Requires-Dist: pywhispercpp ; extra == 'whisper-cpp'
Requires-Python: >=3.11
Project-URL: Homepage, https://github.com/codyw912/open-asr-server
Project-URL: Repository, https://github.com/codyw912/open-asr-server
Project-URL: Issues, https://github.com/codyw912/open-asr-server/issues
Provides-Extra: dev
Provides-Extra: faster-whisper
Provides-Extra: kyutai-mlx
Provides-Extra: lightning-whisper
Provides-Extra: nemo
Provides-Extra: parakeet
Provides-Extra: whisper
Provides-Extra: whisper-cpp
